sellmeier.py
sellmeier/__init__.py
sellmeier/lnsellmeier.py
sellmeier/optical.py
sellmeier/qpm.py
sellmeier/ridgesellmeier.py
sellmeier/sellmeier.py
sellmeier-1.2.dist-info/METADATA
sellmeier-1.2.dist-info/WHEEL
sellmeier-1.2.dist-info/top_level.txt
sellmeier-1.2.dist-info/RECORD
