Metadata-Version: 2.1
Name: sellmeier
Version: 1.2
Summary: Calculate index of refraction or poling period for various nonlinear optical materials.
Home-page: https://github.com/decoherer/sellmeier
Author: decoherer
Author-email: 63128649+decoherer@users.noreply.github.com
Classifier: Programming Language :: Python :: 3
Classifier: License :: OSI Approved :: MIT License
Classifier: Operating System :: OS Independent
Requires-Dist: numpy
Requires-Dist: scipy
Requires-Dist: matplotlib
